Workbook

Sheet 使い方
A1: ボランティアカフェ 第1回 開催準備リスト
A2: 大郷町社会福祉協議会 ボランティアセンター事業
A4: 開催の予定（2026年9月2日時点で確定しているもの）
A5: 開催日 | B5: 46371 | C5: ← ここを直すと、全部の締切日が動きます
A6: 曜日 | B6: =CHOOSE(WEEKDAY(B5),"日曜日","月曜日","火曜日","水曜日","木曜日","金曜日","土曜日") | C6: 緑のセル＝9/2時点で決まっていること
A7: 会場 | B7: 粕川地区防災コミュニティーセンター
A8: 当日 | B8: 9:00 開場 9:30 スタート 12:00 終了
A9: 前日準備 | B9: 12月14日（月）15:00 〜
A10: 予算 | B10: 50,000円
A12: シートの見方
A13: ・「当日の流れ」… 12/14の前日準備から、12/15の片付け・ふりかえりまでの時間割です。
A14: ・「準備リスト」… やることを115項目、締切の早い順にならべています。
A15: ・「逆算スケジュール」… いつ何件たまっているか。人手の山を先に見つけるために使います。
A16: ・「グラフ」… 時期ごと・分野ごとの件数と、進み具合を絵で見るシートです。会議で使えます。
A17: ・「予算50,000円」… 配分のたたき台です。単価と数量を入れ直せば、合計と残額が自動で出ます。
A19: 書き込むところ
A20: ・書き込むのは【担当】【状況】【完了日】【備考】の4列だけです（うすい黄色の列）。ほかの列には計算式が入っています。
A21: ・【状況】はセルを選ぶと「未着手／準備中／完了／対象外」から選べます。「完了」にすると、その行が灰色になります。
A22: ・締切日を過ぎているのに完了していない行は、自動で赤くなります。会議のときは、そこだけ見てください。
A24: 記入例（この形で書いてください）
A25: 締切日 | B25: 分類 | C25: 項目 | D25: 担当 | E25: 状況 | F25: 完了日 | G25: 備考
A26: 46290 | B26: G 盆栽ボランティアの準備 | C26: 盆栽を教えてくれる方と打ち合わせる | D26: 及川 | E26: 準備中 | G26: 高橋文之さんに決定（9/4）
A28: 9月のうちに動くこと
A29: ・町広報への掲載を依頼する — 12月号の原稿締切は10月中〜下旬のことが多く、逆算の8週前では間に合わない可能性があります。まず締切日を確認してください。
A30: ・チラシの原稿をつくる — 10月26日までに役場へ持っていく必要があるため、9月25日までに原稿を仕上げます。
A31: ・盆栽の高橋文之さんと打ち合わせる — 何をどこまでやるか、当日の時間の使い方を9月25日までに相談します。
A32: ・開催伺いの決裁を出す — 予算の執行がここから始まります。
A34: 気をつけたい日
A35: ・9月25日（金）＝ チラシ原稿・盆栽の打ち合わせ・ふりかえりの問いの締切。10/26の役場提出から逆算した前倒し分です。
A36: ・10月26日（月）＝ チラシを役場へ持っていく日。印刷はここまでに終わらせます。
A37: ・11月3日（火）＝ 6週前 は文化の日です。この日に予定していた作業は、前後にずらしてください。
A38: ・11月17日（火）＝ 4週前 までに、防災士の応援人数を確定します。自由見学のコーナー数がここで決まります。
A39: ・12月14日（月）＝ 前日準備です。会場が午後から使えるか確認してください。
A40: ・12月29日（火）＝ 年末で事務所が閉まっている可能性があります。事後の作業は12月28日までに終わる想定で。
A42: 前提と出典：開催日・会場・時間割・予算50,000円は2026年9月2日、項目の削除と期限の変更・盆栽の高橋文之さん・防災士への応援依頼は2026年9月4日に、担当者から示された内容です。もとの96項目は「ボランティアカフェ 開催準備リスト」（volunteer-cafe-checklist.html）から起こし、確定したプログラムと9/4のご指示に合わせて増減しました。「9/25まで」「10/26まで」は開催日から81日前・50日前として計算しています。役場や広報の締切に合わせた外部の期限なので、開催日を動かすときは、この2つだけ実際の締切を確認し直してください。週数から日数への換算と、予算の配分案は、この表の作成時の設定です。

Sheet 当日の流れ
A1: 当日の流れ（12月14日 前日準備 〜 12月15日 開催）
A2: 会場：粕川地区防災コミュニティーセンター ／ 9:00開場 9:30スタート 12:00終了
A4: 時刻 | B4: 場面 | C4: することの中身 | D4: 持ちもの・道具 | E4: 担当
A5: 【12月14日（月）】前日準備
A6: 15:00 | B6: 会場に入る・机いすの配置 | C6: レイアウト図のとおりに。受付／テーブル／講座の席／自由見学のコーナーを分ける | D6: レイアウト図、養生テープ
A7: 15:30 | B7: 掲示物を貼る | C7: 順路の矢印（外の道路からの1枚目がいちばん大事）、受付看板、本日の流れ、各コーナーの表示 | D7: 表示物一式、マスキングテープ
A8: 16:00 | B8: 資機材の搬入・展示 | C8: 災ボラの資機材（スコップ、土のう袋、長靴、軍手、ヘルメット、一輪車）を見学コーナーに並べる | D8: 資機材一式
A9: 16:15 | B9: 盆栽・防災士のコーナーを確認 | C9: 高橋文之さんと防災士に、翌日の立ち位置と持ち場を伝える（前日に来られない場合は当日8:30に） | D9: レイアウト図
A10: 16:30 | B10: 盆栽コーナーの下ごしらえ | C10: シートを敷き、材料と道具を並べる。土がこぼれてよい場所か最終確認 | D10: 苗・鉢・用土・道具・ブルーシート
A11: 17:00 | B11: 給湯・受付の準備、明日の確認 | C11: ポット、紙コップ、名札、参加者カード、記念品。翌朝の集合時刻と鍵を確認 | D11: 備品一式、参加者カード
A12: 【12月15日（火）】当日
A13: 8:30 | B13: 職員集合・最終確認 | C13: 足りないものの買い出しはこの時間に。机いすの数を実際に数える | D13: 積み込みリスト
A14: 9:00 | B14: 開場・受付 | C14: 来た方から名札に呼ばれたい名前を書いてもらう。お茶を出す。早く来た方こそ、話しかける | D14: 受付名簿、名札、サインペン、お茶
A15: 9:30 | B15: スタート・あいさつ | C15: 本日の流れを説明。ひとこと自己紹介（名前＋お題ひとつ）。長く話さなくてよいと最初に伝える | D15: 本日の流れ（掲示）
A16: 10:00 | B16: 講座 前半「ボランティアとは」 | C16: 町でいま動いている活動を写真で紹介。「特別な人がするものではない」を伝える | D16: スライド、配布資料
A17: 10:30 | B17: 講座 後半「災害ボランティアセンターの運営」 | C17: 大郷町で災害が起きたら、どこに、いつ立ち上がるか。受付→ニーズ→マッチング→送り出しの流れ。応援に来た防災士にも一言お願いする | D17: スライド、受付票、ニーズ票
A18: 11:00 | B18: 自由見学（1）コーナーを回る | C18: 災ボラの資機材展示／マッチング体験／町の活動紹介パネル／盆栽コーナー。資機材とマッチングは防災士に、盆栽は高橋文之さんに立ってもらう | D18: 各コーナーの表示
A19: 11:00 | B19: 自由見学（2）お茶と相談 | C19: お茶を飲みながら話す時間。職員は進行せず、様子を見て記録する。はじめての方には必ず誰かがつく | D19: お茶、記録用紙
A20: 11:40 | B20: 次の一歩の案内 | C20: ボランティア登録・活動見学の申し込み。「やってみたいこと」「出られる曜日」を書いてもらう | D20: 登録用紙、見学先リスト
A21: 12:00 | B21: 終了・お見送り | C21: 記念品と次回のご案内を渡す。出口で一人ずつ見送る | D21: 記念品、次回チラシ
A22: 12:00 | B22: 片付け | C22: 資機材の積み込み、盆栽コーナーの清掃、掲示物の回収、ゴミの持ち帰り | D22: ほうき、ゴミ袋
A23: 12:30 | B23: ふりかえり（15分） | C23: 参加者数、はじめて来た人、出た話題、気になった方、つないだ先。次回に変えることを1つだけ決める | D23: 開催記録
A25: ※ 9:30〜10:00 と 11:00〜12:00 の中身は、9/2時点で決まっている枠（10:00〜11:00 講座／11:00〜12:00 自由見学）に合わせた提案です。盆栽は自由見学のコーナーに置く想定で入れていますが、作業に30分以上かかる内容なら別の日に回すことも考えられます。【担当】の列は空けてあります。前日準備の2週間前までに埋めてください。

Sheet 準備リスト
A1: ボランティアカフェ 第1回 準備リスト（開催日からの逆算） | F1: ="開催日："&TEXT(使い方!B5,"yyyy年m月d日")&"（"&CHOOSE(WEEKDAY(使い方!B5),"日","月","火","水","木","金","土")&"） 会場："&使い方!B7
A2: 項目数 | B2: =COUNT($A$5:$A$200) | C2: 完了 | D2: =COUNTIF($I$5:$I$200,"完了") | E2: 残り | F2: =B2-D2 | G2: 締切ぎれ | H2: =SUMPRODUCT(($A$5:$A$200<>"")*($B$5:$B$200<TODAY())*($I$5:$I$200<>"完了")*($I$5:$I$200<>"対象外")) | I2: ※「締切ぎれ」＝ 締切日を過ぎていて、まだ完了していない件数
A4: No | B4: 締切日 | C4: 曜 | D4: 時期 | E4: 分類 | F4: 項目 | G4: 補足・すすめ方 | H4: 担当 | I4: 状況 | J4: 完了日 | K4: 備考
A5: 1 | B5: =使い方!$B$5-81 | C5: =CHOOSE(WEEKDAY(B5),"日","月","火","水","木","金","土") | D5: 9/25まで | E5: C チラシと広報 | F5: チラシの原稿をつくる | G5: ロードマップの「住民のみなさんへ」の文面をそのまま使えます。盆栽と災ボラ体験のことも書き足す | I5: 未着手 | K5: 10/26の役場提出から逆算して9/25まで
A6: 2 | B6: =使い方!$B$5-81 | C6: =CHOOSE(WEEKDAY(B6),"日","月","火","水","木","金","土") | D6: 9/25まで | E6: G 盆栽ボランティアの準備 | F6: 盆栽を教えてくれる方と打ち合わせる | G6: 高橋文之さんに決定（9/4）。何をどこまでやるか、当日の時間の使い方を相談する | I6: 準備中 | K6: 高橋文之さんに決定（9/4）。お願いと打ち合わせはこれから
A7: 3 | B7: =使い方!$B$5-81 | C7: =CHOOSE(WEEKDAY(B7),"日","月","火","水","木","金","土") | D7: 9/25まで | E7: H 災ボラ体験の資料 | F7: ふりかえりの問いを決めておく | G7: 「やってみて、いちばん難しかったのはどこですか」。ここで平時のつながりの話につなげます | I7: 未着手 | K7: 9/25までに前倒し（9/4のご指示）
A8: 4 | B8: =使い方!$B$5-56 | C8: =CHOOSE(WEEKDAY(B8),"日","月","火","水","木","金","土") | D8: 8週前 | E8: A 会場をおさえる | F8: 候補の会場を3か所、実際に見に行く | G8: 駐車場／段差とスロープ／トイレ／お湯が使えるか／歩いて来られる人がいるか | I8: 未着手
A9: 5 | B9: =使い方!$B$5-56 | C9: =CHOOSE(WEEKDAY(B9),"日","月","火","水","木","金","土") | D9: 8週前 | E9: B 事務の手続き | F9: 開催伺いの決裁をとる | G9: ロードマップの企画書を添えて。運営委員会にも報告 | I9: 未着手 | K9: 9月中に。予算執行はここから
A10: 6 | B10: =使い方!$B$5-56 | C10: =CHOOSE(WEEKDAY(B10),"日","月","火","水","木","金","土") | D10: 8週前 | E10: C チラシと広報 | F10: 町広報への掲載を依頼する | G10: 原稿の締切が前月◯日など、かなり早いことがあります。まずこの締切を確認してから開催日を確定する | I10: 未着手 | K10: 9月中に締切日を確認（12月号は10月中〜下旬締切のことが多い）
A11: 7 | B11: =使い方!$B$5-50 | C11: =CHOOSE(WEEKDAY(B11),"日","月","火","水","木","金","土") | D11: 10/26まで | E11: C チラシと広報 | F11: チラシを印刷する | G11: 部数のめやす：回覧用＋窓口＋手渡し用＋掲示用。多めに刷って次回にも使えるよう、日付は刷り込みか別紙かを決める | I11: 未着手 | K11: 10月26日までに役場へ持っていく。予算計上なし（社協内で印刷）
A12: 8 | B12: =使い方!$B$5-49 | C12: =CHOOSE(WEEKDAY(B12),"日","月","火","水","木","金","土") | D12: 7週前 | E12: A 会場をおさえる | F12: 使用申請書を提出。使用料の有無と支払い方法を確認する | I12: 未着手
A13: 9 | B13: =使い方!$B$5-49 | C13: =CHOOSE(WEEKDAY(B13),"日","月","火","水","木","金","土") | D13: 7週前 | E13: D 参加記念品 | F13: 見積をとり、発注する | G13: 納期を確認。名入れをする場合はさらに2週間みる | I13: 未着手 | K13: 7週前に前倒し（9/4のご指示）
A14: 10 | B14: =使い方!$B$5-42 | C14: =CHOOSE(WEEKDAY(B14),"日","月","火","水","木","金","土") | D14: 6週前 | E14: B 事務の手続き | F14: 予算の執行伺い | G14: 記念品／盆栽の材料／茶菓／印刷／講師謝礼 | I14: 未着手 | K14: 予算は50,000円。「予算50,000円」シートの配分案を見ながら
A15: 11 | B15: =使い方!$B$5-42 | C15: =CHOOSE(WEEKDAY(B15),"日","月","火","水","木","金","土") | D15: 6週前 | E15: B 事務の手続き | F15: 予算50,000円の配分を決める | G15: 「予算50,000円」シートのたたき台を見ながら。記念品・盆栽材料・茶菓の3つで大半が決まります | I15: 未着手 | K15: 11月3日は文化の日。前後にずらす
A16: 12 | B16: =使い方!$B$5-42 | C16: =CHOOSE(WEEKDAY(B16),"日","月","火","水","木","金","土") | D16: 6週前 | E16: D 参加記念品 | F16: 何を渡すか決める | G16: 案：花の種の小袋／お茶のティーバッグ／盆栽の小さな苗／町内の作業所でつくったもの（＝作業所支援にもなります） | I16: 未着手 | K16: 11月3日は文化の日。前後にずらす
A17: 13 | B17: =使い方!$B$5-42 | C17: =CHOOSE(WEEKDAY(B17),"日","月","火","水","木","金","土") | D17: 6週前 | E17: D 参加記念品 | F17: 単価と数量を決める | G17: 1人あたりの金額 × 見込み人数 ＋ 予備10個。予算内におさまるか確認 | I17: 未着手 | K17: 11月3日は文化の日。前後にずらす
A18: 14 | B18: =使い方!$B$5-42 | C18: =CHOOSE(WEEKDAY(B18),"日","月","火","水","木","金","土") | D18: 6週前 | E18: G 盆栽ボランティアの準備 | F18: 打ち合わせ：何をどこまでやるか決める | G18: 90分のうち何分使うか（30〜40分がめやす）。作業の難しさ、いすに座ったままできるか | I18: 未着手 | K18: 11月3日は文化の日。前後にずらす
A19: 15 | B19: =使い方!$B$5-42 | C19: =CHOOSE(WEEKDAY(B19),"日","月","火","水","木","金","土") | D19: 6週前 | E19: G 盆栽ボランティアの準備 | F19: 内容を確定する | G19: 案：小さな苗を鉢に植えて持ち帰る／松の芽切り／水やりと置き場所の話。持ち帰れる形にすると満足度が高い | I19: 未着手 | K19: 11月3日は文化の日。前後にずらす
A20: 16 | B20: =使い方!$B$5-42 | C20: =CHOOSE(WEEKDAY(B20),"日","月","火","水","木","金","土") | D20: 6週前 | E20: G 盆栽ボランティアの準備 | F20: 材料の数量を決める | G20: 参加見込み ＋ 予備3セット。当日の飛び込み参加に備える | I20: 未着手 | K20: 11月3日は文化の日。前後にずらす
A21: 17 | B21: =使い方!$B$5-42 | C21: =CHOOSE(WEEKDAY(B21),"日","月","火","水","木","金","土") | D21: 6週前 | E21: G 盆栽ボランティアの準備 | F21: 盆栽を当日どこに入れるか決める | G21: 自由見学（11:00〜12:00）のコーナーに置くのが自然。作業に30分以上かかる内容なら、別の日に回す判断も | I21: 未着手 | K21: 11月3日は文化の日。前後にずらす
A22: 18 | B22: =使い方!$B$5-42 | C22: =CHOOSE(WEEKDAY(B22),"日","月","火","水","木","金","土") | D22: 6週前 | E22: K 体験・展示コーナーの準備 | F22: 町の備蓄にある段ボールベッドの台数を確認し、借用を依頼する | G22: 何台借りられるか、受け取りと返却の方法をあわせて確認する。借用が基本、足りない分だけ購入する | I22: 未着手 | K22: 11月3日は文化の日。前後にずらす
A23: 19 | B23: =使い方!$B$5-42 | C23: =CHOOSE(WEEKDAY(B23),"日","月","火","水","木","金","土") | D23: 6週前 | E23: K 体験・展示コーナーの準備 | F23: 当日使う段ボールベッドの台数を決める | G23: 1台を4〜5人で組むのがめやす。定員50人なら体験用に数台。組み立て済みを1台置いておくと、完成形が分かります | I23: 未着手 | K23: 11月3日は文化の日。前後にずらす
A24: 20 | B24: =使い方!$B$5-42 | C24: =CHOOSE(WEEKDAY(B24),"日","月","火","水","木","金","土") | D24: 6週前 | E24: K 体験・展示コーナーの準備 | F24: 展示する最新の防災グッズを選び、購入リストをつくる | G24: 予算内で。「見たことがない」「さわってみたい」と思えるものを優先する。予算シートは10,000円で計上 | I24: 未着手 | K24: 11月3日は文化の日。前後にずらす
A25: 21 | B25: =使い方!$B$5-42 | C25: =CHOOSE(WEEKDAY(B25),"日","月","火","水","木","金","土") | D25: 6週前 | E25: K 体験・展示コーナーの準備 | F25: 役場総務課防災対策室へ、防災バッグの借用を依頼する | G25: 中身を見せる展示に使います。受け取りと返却の方法、中身を出して並べてよいかもあわせて確認する | I25: 未着手 | K25: 11月3日は文化の日。前後にずらす
A26: 22 | B26: =使い方!$B$5-35 | C26: =CHOOSE(WEEKDAY(B26),"日","月","火","水","木","金","土") | D26: 5週前 | E26: H 災ボラ体験の資料 | F26: 既存の資料一式を出して、そろっているか確認する | G26: 福祉教育プログラム「災害ボランティアセンター運営体験」の様式・進行表 | I26: 未着手
A27: 23 | B27: =使い方!$B$5-35 | C27: =CHOOSE(WEEKDAY(B27),"日","月","火","水","木","金","土") | D27: 5週前 | E27: H 災ボラ体験の資料 | F27: 縮小版の構成を決める | G27: 受付 → ニーズ受付 → マッチング → 送り出し の4場面を、20〜30分で通す。説明は短く、動かす時間を長く | I27: 未着手
A28: 24 | B28: =使い方!$B$5-35 | C28: =CHOOSE(WEEKDAY(B28),"日","月","火","水","木","金","土") | D28: 5週前 | E28: H 災ボラ体験の資料 | F28: 講座（10:00〜11:00）の構成を決める | G28: 前半「ボランティアとは」＋後半「災害ボランティアセンターの運営」。60分をどう割るかを先に決める | I28: 未着手
A29: 25 | B29: =使い方!$B$5-35 | C29: =CHOOSE(WEEKDAY(B29),"日","月","火","水","木","金","土") | D29: 5週前 | E29: H 災ボラ体験の資料 | F29: 講座で話す人を決める | G29: 職員が話すか、外部にお願いするか。外部なら謝礼と依頼文が要ります | I29: 未着手
A30: 26 | B30: =使い方!$B$5-35 | C30: =CHOOSE(WEEKDAY(B30),"日","月","火","水","木","金","土") | D30: 5週前 | E30: H 災ボラ体験の資料 | F30: 大郷町の防災士のうち、誰に応援をお願いするか決める | G30: 町の防災担当課と相談して名簿を確認する。連絡先は持ち出さず、依頼は社協から出す | I30: 未着手
A31: 27 | B31: =使い方!$B$5-35 | C31: =CHOOSE(WEEKDAY(B31),"日","月","火","水","木","金","土") | D31: 5週前 | E31: H 災ボラ体験の資料 | F31: 防災士へ出す応援依頼文をつくる | G31: 1枚に：依頼の趣旨（災害ボランティアセンター運営体験の手伝い）／日時・会場／お願いしたい役割／返事の期限（4週前まで）／社協の連絡先 | I31: 未着手
A32: 28 | B32: =使い方!$B$5-35 | C32: =CHOOSE(WEEKDAY(B32),"日","月","火","水","木","金","土") | D32: 5週前 | E32: K 体験・展示コーナーの準備 | F32: 借りられない不足分の段ボールベッドを購入する | G32: 納期に注意。1台あたり約3,000円。購入するなら、その分どこかを削る必要があります（予算シート参照） | I32: 未着手
A33: 29 | B33: =使い方!$B$5-35 | C33: =CHOOSE(WEEKDAY(B33),"日","月","火","水","木","金","土") | D33: 5週前 | E33: K 体験・展示コーナーの準備 | F33: 防災グッズを発注・購入する | G33: 納期に注意。届いたら箱から出して、当日すぐさわれる状態にしておく | I33: 未着手
A34: 30 | B34: =使い方!$B$5-35 | C34: =CHOOSE(WEEKDAY(B34),"日","月","火","水","木","金","土") | D34: 5週前 | E34: K 体験・展示コーナーの準備 | F34: 配食ボランティアのみなさんへ、当日の紹介コーナーへの協力をお願いする | G34: 写真をお借りするだけでも構いません。当日コーナーに立ってもらえるかも確認する | I34: 未着手
A35: 31 | B35: =使い方!$B$5-28 | C35: =CHOOSE(WEEKDAY(B35),"日","月","火","水","木","金","土") | D35: 4週前 | E35: A 会場をおさえる | F35: 設備を確認する | G35: 電源の位置と数／暖房／給湯室／机といすの数／ゴミは持ち帰りか／掲示物を壁に貼ってよいか | I35: 未着手
A36: 32 | B36: =使い方!$B$5-28 | C36: =CHOOSE(WEEKDAY(B36),"日","月","火","水","木","金","土") | D36: 4週前 | E36: A 会場をおさえる | F36: 前日12月14日（月）15:00から会場に入れるか確認する | G36: 粕川地区防災コミュニティーセンター。前日準備の時間帯に使用申請が要るかも確認 | I36: 未着手 | K36: 会場は粕川地区防災コミュニティーセンターに決定済み
A37: 33 | B37: =使い方!$B$5-28 | C37: =CHOOSE(WEEKDAY(B37),"日","月","火","水","木","金","土") | D37: 4週前 | E37: B 事務の手続き | F37: ボランティア活動保険の加入状況を確認する | G37: 盆栽の道具（はさみ）と災ボラ体験の資機材を扱います。参加者に保険が要るかを整理し、必要なら加入用紙を用意 | I37: 未着手
A38: 34 | B38: =使い方!$B$5-28 | C38: =CHOOSE(WEEKDAY(B38),"日","月","火","水","木","金","土") | D38: 4週前 | E38: C チラシと広報 | F38: 区長・行政区へ回覧を依頼する | G38: 回りきるまで2〜3週間かかります。開催3週前には回りはじめるよう逆算 | I38: 未着手
A39: 35 | B39: =使い方!$B$5-28 | C39: =CHOOSE(WEEKDAY(B39),"日","月","火","水","木","金","土") | D39: 4週前 | E39: E カフェで使う備品 | F39: 飲みもの | G39: お茶（温・冷）／コーヒー／紅茶／砂糖・ミルク／麦茶。夏冬で入れ替える | I39: 未着手
A40: 36 | B40: =使い方!$B$5-28 | C40: =CHOOSE(WEEKDAY(B40),"日","月","火","水","木","金","土") | D40: 4週前 | E40: E カフェで使う備品 | F40: 紙コップ・紙皿・おしぼり・つまようじ・ゴミ袋（分別の数だけ） | I40: 未着手
A41: 37 | B41: =使い方!$B$5-28 | C41: =CHOOSE(WEEKDAY(B41),"日","月","火","水","木","金","土") | D41: 4週前 | E41: E カフェで使う備品 | F41: 保温ポット2本、やかん、給湯の段取り | G41: 会場で沸かせるか、社協から運ぶかを決めておく | I41: 未着手
A42: 38 | B42: =使い方!$B$5-28 | C42: =CHOOSE(WEEKDAY(B42),"日","月","火","水","木","金","土") | D42: 4週前 | E42: E カフェで使う備品 | F42: 名札（貼るタイプ）とケース、太めのサインペン | G42: 呼ばれたい名前を大きく書いてもらいます。細いペンは使わない | I42: 未着手
A43: 39 | B43: =使い方!$B$5-28 | C43: =CHOOSE(WEEKDAY(B43),"日","月","火","水","木","金","土") | D43: 4週前 | E43: F 会場に貼る表示物 | F43: 自由見学（11:00〜12:00）のコーナー構成を決める | G43: 案：災ボラの資機材展示／マッチング体験／町の活動紹介パネル／盆栽コーナー／お茶と相談。何を何か所置くかを先に決める | I43: 未着手
A44: 40 | B44: =使い方!$B$5-28 | C44: =CHOOSE(WEEKDAY(B44),"日","月","火","水","木","金","土") | D44: 4週前 | E44: G 盆栽ボランティアの準備 | F44: 材料を発注する | G44: 苗木／鉢／用土／鉢底ネット／鉢底石／化粧砂／ラベル | I44: 未着手
A45: 41 | B45: =使い方!$B$5-28 | C45: =CHOOSE(WEEKDAY(B45),"日","月","火","水","木","金","土") | D45: 4週前 | E45: G 盆栽ボランティアの準備 | F45: 道具をそろえる | G45: 剪定ばさみ（人数分は要りません。3〜4本を回す）／ピンセット／じょうろ／園芸用の針金／割り箸／土入れ | I45: 未着手 | K45: 予算計上なし。手持ちや借用でまかなう
A46: 42 | B46: =使い方!$B$5-28 | C46: =CHOOSE(WEEKDAY(B46),"日","月","火","水","木","金","土") | D46: 4週前 | E46: H 災ボラ体験の資料 | F46: ボランティア受付票を必要部数印刷する | I46: 未着手
A47: 43 | B47: =使い方!$B$5-28 | C47: =CHOOSE(WEEKDAY(B47),"日","月","火","水","木","金","土") | D47: 4週前 | E47: H 災ボラ体験の資料 | F47: ニーズ受付票を印刷し、想定の事例を5〜8件つくる | G47: 大郷町で実際に起こりうる困りごとで。「二階まで水が来た」「ひとり暮らしで家財が出せない」など、地名を入れると急に自分ごとになります | I47: 未着手
A48: 44 | B48: =使い方!$B$5-28 | C48: =CHOOSE(WEEKDAY(B48),"日","月","火","水","木","金","土") | D48: 4週前 | E48: H 災ボラ体験の資料 | F48: 防災士へ依頼文を出し、来てくれる人と当日の役割を決める | G48: 役割の案：資機材の説明、マッチング体験の進行、受付の補助。何人来られるかで自由見学のコーナー数が決まります | I48: 未着手 | K48: 4週前（11/17）までに人数を確定する
A49: 45 | B49: =使い方!$B$5-21 | C49: =CHOOSE(WEEKDAY(B49),"日","月","火","水","木","金","土") | D49: 3週前 | E49: A 会場をおさえる | F49: 当日は9:00開場のため、8:30に鍵を開けられるか確認する | G49: 職員集合は8:30。鍵の受け取り方と、当日の連絡先もあわせて | I49: 未着手
A50: 46 | B50: =使い方!$B$5-21 | C50: =CHOOSE(WEEKDAY(B50),"日","月","火","水","木","金","土") | D50: 3週前 | E50: B 事務の手続き | F50: 個人情報の扱いを決める | G50: 参加者カードの保管場所・保管期間・持ち出しの可否。世話人・協力者にも書面で説明 | I50: 未着手
A51: 47 | B51: =使い方!$B$5-21 | C51: =CHOOSE(WEEKDAY(B51),"日","月","火","水","木","金","土") | D51: 3週前 | E51: B 事務の手続き | F51: 写真撮影の同意の取り方を決める | G51: 受付での口頭確認と、会場の掲示。写りたくない方の名札に印をつける方法まで | I51: 未着手
A52: 48 | B52: =使い方!$B$5-21 | C52: =CHOOSE(WEEKDAY(B52),"日","月","火","水","木","金","土") | D52: 3週前 | E52: C チラシと広報 | F52: 掲示をお願いして回る | G52: 公民館／支所／診療所／商店／郵便局／スーパー／温泉施設／集会所 | I52: 未着手
A53: 49 | B53: =使い方!$B$5-21 | C53: =CHOOSE(WEEKDAY(B53),"日","月","火","水","木","金","土") | D53: 3週前 | E53: C チラシと広報 | F53: 直接声をかける（まず20人） | G53: ボランティア入門講座の修了者／サロン参加者／登録ボランティア。名簿を見ながら、電話か手渡しで | I53: 未着手
A54: 50 | B54: =使い方!$B$5-21 | C54: =CHOOSE(WEEKDAY(B54),"日","月","火","水","木","金","土") | D54: 3週前 | E54: C チラシと広報 | F54: 民生委員児童委員・地区社協・地域包括支援センターへ情報提供 | G54: 気になっている方に声をかけてもらう。「誘ってあげてください」と具体的に頼む | I54: 未着手
A55: 51 | B55: =使い方!$B$5-21 | C55: =CHOOSE(WEEKDAY(B55),"日","月","火","水","木","金","土") | D55: 3週前 | E55: C チラシと広報 | F55: ホームページ・SNSに掲載する | I55: 未着手
A56: 52 | B56: =使い方!$B$5-21 | C56: =CHOOSE(WEEKDAY(B56),"日","月","火","水","木","金","土") | D56: 3週前 | E56: D 参加記念品 | F56: 納品を確認し、数を数える | I56: 未着手
A57: 53 | B57: =使い方!$B$5-21 | C57: =CHOOSE(WEEKDAY(B57),"日","月","火","水","木","金","土") | D57: 3週前 | E57: F 会場に貼る表示物 | F57: 建物の入口から会場までの順路表示（矢印を3枚以上） | G57: はじめての方は、入口で引き返します。外の道路からの1枚目がいちばん大事 | I57: 未着手
A58: 54 | B58: =使い方!$B$5-21 | C58: =CHOOSE(WEEKDAY(B58),"日","月","火","水","木","金","土") | D58: 3週前 | E58: F 会場に貼る表示物 | F58: 受付の看板「ボランティアカフェ 受付」 | I58: 未着手
A59: 55 | B59: =使い方!$B$5-21 | C59: =CHOOSE(WEEKDAY(B59),"日","月","火","水","木","金","土") | D59: 3週前 | E59: F 会場に貼る表示物 | F59: 本日の流れ（90分の進行を大きく1枚） | G59: 途中から来た方が、見れば分かるように | I59: 未着手
A60: 56 | B60: =使い方!$B$5-21 | C60: =CHOOSE(WEEKDAY(B60),"日","月","火","水","木","金","土") | D60: 3週前 | E60: F 会場に貼る表示物 | F60: テーブル番号（1〜4） | I60: 未着手
A61: 57 | B61: =使い方!$B$5-21 | C61: =CHOOSE(WEEKDAY(B61),"日","月","火","水","木","金","土") | D61: 3週前 | E61: F 会場に貼る表示物 | F61: 「写真を撮ります。写りたくない方は受付でお申し出ください」の掲示 | I61: 未着手
A62: 58 | B62: =使い方!$B$5-21 | C62: =CHOOSE(WEEKDAY(B62),"日","月","火","水","木","金","土") | D62: 3週前 | E62: G 盆栽ボランティアの準備 | F62: 汚れ対策をそろえる | G62: ブルーシート／新聞紙／テーブルに敷くもの／雑巾／バケツ／ほうきとちりとり | I62: 未着手
A63: 59 | B63: =使い方!$B$5-21 | C63: =CHOOSE(WEEKDAY(B63),"日","月","火","水","木","金","土") | D63: 3週前 | E63: G 盆栽ボランティアの準備 | F63: 軍手（人数分＋予備5） | G63: 手の汚れを気にして参加をやめる方がいます。軍手は必ず余分に | I63: 未着手
A64: 60 | B64: =使い方!$B$5-21 | C64: =CHOOSE(WEEKDAY(B64),"日","月","火","水","木","金","土") | D64: 3週前 | E64: G 盆栽ボランティアの準備 | F64: 手洗い場所と、そこまでの動線を決める | G64: 土のついた手で歩く道すじに、新聞紙を敷いておく | I64: 未着手
A65: 61 | B65: =使い方!$B$5-21 | C65: =CHOOSE(WEEKDAY(B65),"日","月","火","水","木","金","土") | D65: 3週前 | E65: H 災ボラ体験の資料 | F65: マッチング用のボードをつくる | G65: 模造紙とカード、マグネットかマスキングテープ。人数と作業内容を貼り合わせる形に | I65: 未着手
A66: 62 | B66: =使い方!$B$5-21 | C66: =CHOOSE(WEEKDAY(B66),"日","月","火","水","木","金","土") | D66: 3週前 | E66: H 災ボラ体験の資料 | F66: 役割の名札をつくる | G66: 受付／ニーズ／マッチング／資材／送り出し。首から下げる形にすると、役になりきれます | I66: 未着手
A67: 63 | B67: =使い方!$B$5-21 | C67: =CHOOSE(WEEKDAY(B67),"日","月","火","水","木","金","土") | D67: 3週前 | E67: H 災ボラ体験の資料 | F67: 資機材の見本を1つずつ用意する | G67: スコップ／土のう袋／長靴／軍手／ヘルメット／一輪車。写真より、本物が1つあるほうが伝わります | I67: 未着手
A68: 64 | B68: =使い方!$B$5-21 | C68: =CHOOSE(WEEKDAY(B68),"日","月","火","水","木","金","土") | D68: 3週前 | E68: H 災ボラ体験の資料 | F68: 説明用の掲示をつくる | G68: 「大郷町で災害が起きたら、災害ボランティアセンターはどこに、いつ立ち上がるか」を1枚に | I68: 未着手
A69: 65 | B69: =使い方!$B$5-21 | C69: =CHOOSE(WEEKDAY(B69),"日","月","火","水","木","金","土") | D69: 3週前 | E69: H 災ボラ体験の資料 | F69: ボランティア活動保険の説明資料と加入用紙を用意する | I69: 未着手
A70: 66 | B70: =使い方!$B$5-21 | C70: =CHOOSE(WEEKDAY(B70),"日","月","火","水","木","金","土") | D70: 3週前 | E70: H 災ボラ体験の資料 | F70: 講座の資料・スライドをつくる | G70: 配布資料は文字を大きく。60分は長いので、途中に手を動かす時間か問いかけを入れる | I70: 未着手
A71: 67 | B71: =使い方!$B$5-21 | C71: =CHOOSE(WEEKDAY(B71),"日","月","火","水","木","金","土") | D71: 3週前 | E71: K 体験・展示コーナーの準備 | F71: 段ボールベッドの受け取り・運搬・返却の段取りを決める | G71: 前日12/14の準備に間に合うように。かさばるので、運ぶ車と置き場所を先に決めておく | I71: 未着手
A72: 68 | B72: =使い方!$B$5-21 | C72: =CHOOSE(WEEKDAY(B72),"日","月","火","水","木","金","土") | D72: 3週前 | E72: K 体験・展示コーナーの準備 | F72: 段ボールベッドの組み立て手順を、大きく1枚に書き出す | G72: 写真かイラストで3〜4ステップ。コーナーに貼っておけば、職員がつきっきりにならずにすみます | I72: 未着手
A73: 69 | B73: =使い方!$B$5-21 | C73: =CHOOSE(WEEKDAY(B73),"日","月","火","水","木","金","土") | D73: 3週前 | E73: K 体験・展示コーナーの準備 | F73: 防災グッズと防災バッグの並べ方を決め、説明札をつくる | G73: バッグの中身は出して並べる。一つずつに「なぜ要るか」を一言そえると、見るだけで学びになります | I73: 未着手
A74: 70 | B74: =使い方!$B$5-21 | C74: =CHOOSE(WEEKDAY(B74),"日","月","火","水","木","金","土") | D74: 3週前 | E74: K 体験・展示コーナーの準備 | F74: 配食ボランティアの紹介パネル・写真を用意する | G74: 活動のようすが分かる写真を数枚。町の活動紹介のコーナーにまとめて貼る | I74: 未着手
A75: 71 | B75: =使い方!$B$5-14 | C75: =CHOOSE(WEEKDAY(B75),"日","月","火","水","木","金","土") | D75: 2週前 | E75: A 会場をおさえる | F75: レイアウト図をつくる | G75: 受付／テーブル4つ／盆栽コーナー／災ボラ体験コーナー／給湯・ゴミ／記念品の置き場 | I75: 未着手
A76: 72 | B76: =使い方!$B$5-14 | C76: =CHOOSE(WEEKDAY(B76),"日","月","火","水","木","金","土") | D76: 2週前 | E76: B 事務の手続き | F76: 食物アレルギーの対応を決める | G76: お菓子は個包装で、表示のあるものを。空袋を当日まで残しておく | I76: 未着手
A77: 73 | B77: =使い方!$B$5-14 | C77: =CHOOSE(WEEKDAY(B77),"日","月","火","水","木","金","土") | D77: 2週前 | E77: D 参加記念品 | F77: 添えるカードをつくる | G77: 「次回は◯月◯日です」「お問い合わせはボランティアセンターへ」。次につながる一言を入れる | I77: 未着手
A78: 74 | B78: =使い方!$B$5-14 | C78: =CHOOSE(WEEKDAY(B78),"日","月","火","水","木","金","土") | D78: 2週前 | E78: D 参加記念品 | F78: 袋詰めをする | G78: 記念品＋カード＋次回チラシをセットに。当日あわてないよう、前もって | I78: 未着手
A79: 75 | B79: =使い方!$B$5-14 | C79: =CHOOSE(WEEKDAY(B79),"日","月","火","水","木","金","土") | D79: 2週前 | E79: E カフェで使う備品 | F79: 参加者カード、筆記用具、クリップボード、受付名簿 | I79: 未着手
A80: 76 | B80: =使い方!$B$5-14 | C80: =CHOOSE(WEEKDAY(B80),"日","月","火","水","木","金","土") | D80: 2週前 | E80: E カフェで使う備品 | F80: テーブルクロス、花か観葉植物（1テーブルに1つ） | G80: 「会議」ではなく「カフェ」に見せるための、いちばん安い方法です | I80: 未着手
A81: 77 | B81: =使い方!$B$5-14 | C81: =CHOOSE(WEEKDAY(B81),"日","月","火","水","木","金","土") | D81: 2週前 | E81: E カフェで使う備品 | F81: 小さなスピーカー（BGM用・小音量） | G81: 沈黙が気にならなくなり、はじめての方が入りやすくなります | I81: 未着手
A82: 78 | B82: =使い方!$B$5-14 | C82: =CHOOSE(WEEKDAY(B82),"日","月","火","水","木","金","土") | D82: 2週前 | E82: E カフェで使う備品 | F82: 救急箱、消毒、絆創膏、体温計、ティッシュ | G82: 盆栽ではさみを使うため、絆創膏は多めに | I82: 未着手
A83: 79 | B83: =使い方!$B$5-14 | C83: =CHOOSE(WEEKDAY(B83),"日","月","火","水","木","金","土") | D83: 2週前 | E83: E カフェで使う備品 | F83: カメラ（記録用）、予備の電池 | I83: 未着手
A84: 80 | B84: =使い方!$B$5-14 | C84: =CHOOSE(WEEKDAY(B84),"日","月","火","水","木","金","土") | D84: 2週前 | E84: E カフェで使う備品 | F84: マスキングテープ、養生テープ、模造紙、はさみ、油性ペン | I84: 未着手
A85: 81 | B85: =使い方!$B$5-14 | C85: =CHOOSE(WEEKDAY(B85),"日","月","火","水","木","金","土") | D85: 2週前 | E85: F 会場に貼る表示物 | F85: 盆栽コーナーの表示と、手順の掲示 | G85: 「土を入れる → 苗を置く → 水をやる」を、写真かイラストで3ステップに | I85: 未着手
A86: 82 | B86: =使い方!$B$5-14 | C86: =CHOOSE(WEEKDAY(B86),"日","月","火","水","木","金","土") | D86: 2週前 | E86: F 会場に貼る表示物 | F86: 災ボラ体験コーナーの表示（受付／ニーズ受付／マッチング／送り出しの4か所） | G86: 本物の災害ボランティアセンターと同じ順に並べる。これ自体が説明になります | I86: 未着手
A87: 83 | B87: =使い方!$B$5-14 | C87: =CHOOSE(WEEKDAY(B87),"日","月","火","水","木","金","土") | D87: 2週前 | E87: F 会場に貼る表示物 | F87: 次回のご案内（日付を大きく1枚） | G87: 帰りぎわに必ず目に入る位置へ | I87: 未着手
A88: 84 | B88: =使い方!$B$5-14 | C88: =CHOOSE(WEEKDAY(B88),"日","月","火","水","木","金","土") | D88: 2週前 | E88: F 会場に貼る表示物 | F88: ボランティア登録・活動見学のご案内 | G88: 用紙を横に置いておく。その場で書いて帰れるように | I88: 未着手
A89: 85 | B89: =使い方!$B$5-14 | C89: =CHOOSE(WEEKDAY(B89),"日","月","火","水","木","金","土") | D89: 2週前 | E89: F 会場に貼る表示物 | F89: 町でいま動いている活動の紹介パネル | G89: 配食・見守り・サロン・除雪。写真を貼るだけでよい | I89: 未着手
A90: 86 | B90: =使い方!$B$5-14 | C90: =CHOOSE(WEEKDAY(B90),"日","月","火","水","木","金","土") | D90: 2週前 | E90: G 盆栽ボランティアの準備 | F90: 「育て方」の1枚をつくって印刷する | G90: 水やり／置き場所／冬の越し方／困ったときの連絡先。持ち帰ったあとも社協とつながる紙になります | I90: 未着手
A91: 87 | B91: =使い方!$B$5-14 | C91: =CHOOSE(WEEKDAY(B91),"日","月","火","水","木","金","土") | D91: 2週前 | E91: G 盆栽ボランティアの準備 | F91: けがへの備えを確認する | G91: はさみを使います。保険の対象になるか、応急手当の担当は誰か | I91: 未着手
A92: 88 | B92: =使い方!$B$5-14 | C92: =CHOOSE(WEEKDAY(B92),"日","月","火","水","木","金","土") | D92: 2週前 | E92: H 災ボラ体験の資料 | F92: 進行台本をつくる | G92: 誰がどの役をやり、何を言うか。参加者が少なかった場合の縮め方も書いておく | I92: 未着手
A93: 89 | B93: =使い方!$B$5-14 | C93: =CHOOSE(WEEKDAY(B93),"日","月","火","水","木","金","土") | D93: 2週前 | E93: I 当日の運営 | F93: 役割分担表をつくる | G93: 受付／お茶／進行／盆栽の補助／災ボラ／記録・写真／片付け。ひとり2役までにする | I93: 未着手
A94: 90 | B94: =使い方!$B$5-14 | C94: =CHOOSE(WEEKDAY(B94),"日","月","火","水","木","金","土") | D94: 2週前 | E94: I 当日の運営 | F94: 進行台本と、分単位のタイムテーブルをつくる | G94: 盆栽と災ボラを入れると90分は窮屈です。どちらかを次回に回す判断も、ここで決めておく | I94: 未着手
A95: 91 | B95: =使い方!$B$5-14 | C95: =CHOOSE(WEEKDAY(B95),"日","月","火","水","木","金","土") | D95: 2週前 | E95: I 当日の運営 | F95: 台本とレイアウト図を、関わる全員に配る | G95: 講師・世話人候補・協力者にも。当日はじめて渡さない | I95: 未着手
A96: 92 | B96: =使い方!$B$5-14 | C96: =CHOOSE(WEEKDAY(B96),"日","月","火","水","木","金","土") | D96: 2週前 | E96: I 当日の運営 | F96: 前日準備（12/14 15:00〜）の段取りと担当を決める | G96: 会場設営、机いすの配置、掲示、資機材の搬入、盆栽コーナーの下ごしらえ、給湯の確認 | I96: 未着手
... A98: 94 | B98: =使い方!$B$5-14 | C98: =CHOOSE(WEEKDAY(B98),"日","月","火","水","木","金","土") | D98: 2週前 | E98: K 体験・展示コーナーの準備 | F98: 段ボールベッドの組み立てと解体を、職員で一度やってみる | G98: 当日説明できるようになるため。何分かかるかを測っておくと、体験の時間配分が決められます | I98: 未着手
A99: 95 | B99: =使い方!$B$5-7 | C99: =CHOOSE(WEEKDAY(B99),"日","月","火","水","木","金","土") | D99: 1週前 | E99: C チラシと広報 | F99: 参加の見込み数をまとめる | G99: 茶菓・記念品・盆栽材料の数を決めるため。予備を3〜5人分みておく | I99: 未着手
A100: 96 | B100: =使い方!$B$5-7 | C100: =CHOOSE(WEEKDAY(B100),"日","月","火","水","木","金","土") | D100: 1週前 | E100: E カフェで使う備品 | F100: お菓子 | G100: 個包装で、原材料表示のあるもの。やわらかいものも用意する（入れ歯の方のため） | I100: 未着手
A101: 97 | B101: =使い方!$B$5-7 | C101: =CHOOSE(WEEKDAY(B101),"日","月","火","水","木","金","土") | D101: 1週前 | E101: I 当日の運営 | F101: 動線のリハーサルをする（30分でよい） | G101: 入口から受付、席、盆栽コーナー、手洗い、災ボラコーナーまで、実際に歩いてみる | I101: 未着手
A102: 98 | B102: =使い方!$B$5-1 | C102: =CHOOSE(WEEKDAY(B102),"日","月","火","水","木","金","土") | D102: 前日 | E102: B 事務の手続き | F102: 会場使用料の支払い | G102: 参加費を取らないことになったため、釣り銭の準備は不要 | I102: 未着手
...

Sheet 逆算スケジュール
A1: 逆算スケジュール いつ、何が締切になるか
A2: 件数は「準備リスト」から自動で数えています。件数の多い週が、人手のいる週です。
A4: 締切日 | B4: 曜 | C4: 時期 | D4: この時期の山場 | E4: 件数 | F4: 完了 | G4: 残り | H4: 気をつけること
A5: =使い方!$B$5-81 | B5: =CHOOSE(WEEKDAY(A5),"日","月","火","水","木","金","土") | C5: 9/25まで | D5: チラシの原稿、盆栽の打ち合わせ、ふりかえりの問い。10/26の役場提出から逆算した前倒し分 | E5: =COUNTIF(準備リスト!$D$5:$D$119,$C5) | F5: =COUNTIFS(準備リスト!$D$5:$D$119,$C5,準備リスト!$I$5:$I$119,"完了") | G5: =E5-F5 | H5: 9/25（金）。開催日を動かすときは、ここも見直す
A6: =使い方!$B$5-56 | B6: =CHOOSE(WEEKDAY(A6),"日","月","火","水","木","金","土") | C6: 8週前 | D6: 町広報の掲載締切を確認する。開催伺いの決裁を出す | E6: =COUNTIF(準備リスト!$D$5:$D$119,$C6) | F6: =COUNTIFS(準備リスト!$D$5:$D$119,$C6,準備リスト!$I$5:$I$119,"完了") | G6: =E6-F6 | H6: 10/20。広報は9月中に動く
A7: =使い方!$B$5-50 | B7: =CHOOSE(WEEKDAY(A7),"日","月","火","水","木","金","土") | C7: 10/26まで | D7: チラシの印刷を終える | E7: =COUNTIF(準備リスト!$D$5:$D$119,$C7) | F7: =COUNTIFS(準備リスト!$D$5:$D$119,$C7,準備リスト!$I$5:$I$119,"完了") | G7: =E7-F7 | H7: 10/26までに役場へ持っていく必要があります
A8: =使い方!$B$5-49 | B8: =CHOOSE(WEEKDAY(A8),"日","月","火","水","木","金","土") | C8: 7週前 | D8: 会場の使用申請。参加記念品の見積と発注 | E8: =COUNTIF(準備リスト!$D$5:$D$119,$C8) | F8: =COUNTIFS(準備リスト!$D$5:$D$119,$C8,準備リスト!$I$5:$I$119,"完了") | G8: =E8-F8
A9: =使い方!$B$5-42 | B9: =CHOOSE(WEEKDAY(A9),"日","月","火","水","木","金","土") | C9: 6週前 | D9: 予算の配分を決める。段ボールベッドの借用・台数、防災グッズの購入リスト、防災バッグの借用を依頼する | E9: =COUNTIF(準備リスト!$D$5:$D$119,$C9) | F9: =COUNTIFS(準備リスト!$D$5:$D$119,$C9,準備リスト!$I$5:$I$119,"完了") | G9: =E9-F9 | H9: 11/3は文化の日。前後にずらす
A10: =使い方!$B$5-35 | B10: =CHOOSE(WEEKDAY(A10),"日","月","火","水","木","金","土") | C10: 5週前 | D10: 講座の構成と話す人を決める。防災士へ依頼文を出す。防災グッズと段ボールベッド不足分を発注する | E10: =COUNTIF(準備リスト!$D$5:$D$119,$C10) | F10: =COUNTIFS(準備リスト!$D$5:$D$119,$C10,準備リスト!$I$5:$I$119,"完了") | G10: =E10-F10 | H10: 発注の納期に注意
A11: =使い方!$B$5-28 | B11: =CHOOSE(WEEKDAY(A11),"日","月","火","水","木","金","土") | C11: 4週前 | D11: 回覧を依頼（回りきるのに2〜3週）。盆栽の材料を発注。防災士の応援人数を確定する | E11: =COUNTIF(準備リスト!$D$5:$D$119,$C11) | F11: =COUNTIFS(準備リスト!$D$5:$D$119,$C11,準備リスト!$I$5:$I$119,"完了") | G11: =E11-F11 | H11: 自由見学のコーナー数は、防災士が何人来られるかで決まります
A12: =使い方!$B$5-21 | B12: =CHOOSE(WEEKDAY(A12),"日","月","火","水","木","金","土") | C12: 3週前 | D12: 直接声かけを始める。掲示を各所へ。表示物・講座資料・各コーナーの説明札をつくる | E12: =COUNTIF(準備リスト!$D$5:$D$119,$C12) | F12: =COUNTIFS(準備リスト!$D$5:$D$119,$C12,準備リスト!$I$5:$I$119,"完了") | G12: =E12-F12 | H12: ここがいちばん忙しい週
A13: =使い方!$B$5-14 | B13: =CHOOSE(WEEKDAY(A13),"日","月","火","水","木","金","土") | C13: 2週前 | D13: 役割分担と進行台本。レイアウト図。段ボールベッドの組み立て練習。記念品の袋詰め | E13: =COUNTIF(準備リスト!$D$5:$D$119,$C13) | F13: =COUNTIFS(準備リスト!$D$5:$D$119,$C13,準備リスト!$I$5:$I$119,"完了") | G13: =E13-F13 | H13: 12月の行事と重なりやすい
A14: =使い方!$B$5-7 | B14: =CHOOSE(WEEKDAY(A14),"日","月","火","水","木","金","土") | C14: 1週前 | D14: 動線のリハーサル（30分）。材料と備品の最終確認。参加見込み数を固める | E14: =COUNTIF(準備リスト!$D$5:$D$119,$C14) | F14: =COUNTIFS(準備リスト!$D$5:$D$119,$C14,準備リスト!$I$5:$I$119,"完了") | G14: =E14-F14
A15: =使い方!$B$5-1 | B15: =CHOOSE(WEEKDAY(A15),"日","月","火","水","木","金","土") | C15: 前日 | D15: 12/14（月）15:00から会場設営。声をかけた方へリマインドの電話 | E15: =COUNTIF(準備リスト!$D$5:$D$119,$C15) | F15: =COUNTIFS(準備リスト!$D$5:$D$119,$C15,準備リスト!$I$5:$I$119,"完了") | G15: =E15-F15 | H15: 会場が午後から使えるか確認
A16: =使い方!$B$5+0 | B16: =CHOOSE(WEEKDAY(A16),"日","月","火","水","木","金","土") | C16: 当日 | D16: 8:30集合。9:00開場、9:30スタート、12:00終了 | E16: =COUNTIF(準備リスト!$D$5:$D$119,$C16) | F16: =COUNTIFS(準備リスト!$D$5:$D$119,$C16,準備リスト!$I$5:$I$119,"完了") | G16: =E16-F16 | H16: 「当日の流れ」シートを見ながら
A17: =使い方!$B$5+0 | B17: =CHOOSE(WEEKDAY(A17),"日","月","火","水","木","金","土") | C17: 当日中 | D17: 片付けのあと、15分でふりかえり。開催記録を書く | E17: =COUNTIF(準備リスト!$D$5:$D$119,$C17) | F17: =COUNTIFS(準備リスト!$D$5:$D$119,$C17,準備リスト!$I$5:$I$119,"完了") | G17: =E17-F17 | H17: その場で書かないと忘れます
A18: =使い方!$B$5+3 | B18: =CHOOSE(WEEKDAY(A18),"日","月","火","水","木","金","土") | C18: 3日以内 | D18: 講師・協力者・会場へお礼 | E18: =COUNTIF(準備リスト!$D$5:$D$119,$C18) | F18: =COUNTIFS(準備リスト!$D$5:$D$119,$C18,準備リスト!$I$5:$I$119,"完了") | G18: =E18-F18 | H18: 高橋文之さんへは写真を添えて
A19: =使い方!$B$5+7 | B19: =CHOOSE(WEEKDAY(A19),"日","月","火","水","木","金","土") | C19: 1週以内 | D19: 写真の整理、精算、参加者へ次回のお知らせ | E19: =COUNTIF(準備リスト!$D$5:$D$119,$C19) | F19: =COUNTIFS(準備リスト!$D$5:$D$119,$C19,準備リスト!$I$5:$I$119,"完了") | G19: =E19-F19 | H19: 12/22。年内に済ませる
A20: =使い方!$B$5+14 | B20: =CHOOSE(WEEKDAY(A20),"日","月","火","水","木","金","土") | C20: 2週以内 | D20: 運営委員会・事務局へ報告。参加者カードの整理。盆栽の続き希望者へ連絡 | E20: =COUNTIF(準備リスト!$D$5:$D$119,$C20) | F20: =COUNTIFS(準備リスト!$D$5:$D$119,$C20,準備リスト!$I$5:$I$119,"完了") | G20: =E20-F20 | H20: 12/29は年末休みの可能性。12/28までに
D21: 合計 | E21: =SUM(E5:E20) | F21: =SUM(F5:F20) | G21: =SUM(G5:G20)

Sheet 予算50,000円
A1: 予算 50,000円 配分のたたき台
A2: 黄色いセル（単価・数量）を入れ直すと、金額・合計・残額が自動で計算し直されます。
A4: 予算の総額 | B4: 50000 | C4: ← 9/2時点で示された額
A5: 参加者の見込み | B5: 50 | C5: ← 数量の計算に使っています
A7: 費目 | B7: 内訳・考え方 | C7: 単価 | D7: 数量 | E7: 金額 | F7: 備考
A8: 茶菓・飲みもの | B8: お茶・コーヒー・お菓子。定員50人＋予備5人分 | C8: 150 | D8: =$B$5+5 | E8: =C8*D8 | F8: 個包装で、原材料表示のあるもの
A9: 参加記念品 | B9: 持ち帰って家で目に入るもの。次回の日付を書いたカードを添える | C9: 150 | D9: =$B$5+5 | E9: =C9*D9 | F9: 町内の作業所でつくったものにすると、作業所支援にもなります
A10: 最新の防災グッズ | B10: 展示用に購入する。さわれるようにして並べる | C10: 10000 | D10: 1 | E10: =C10*D10 | F10: 「見たことがない」「さわってみたい」と思えるものを優先する
A11: 段ボールベッド | B11: 町の備蓄から借り、不足分だけ購入する | C11: 3000 | D11: 0 | E11: =C11*D11 | F11: 借用でまかなう想定のため数量0。購入するなら台数を入れてください（1台あたり約3,000円）
A12: 盆栽の材料 | B12: 苗・鉢・用土・鉢底ネット・化粧砂。1人1セット | C12: 700 | D12: 15 | E12: =C12*D12 | F12: 希望者15人分。参加者全員分は予算に入りません
A13: 印刷 | B13: チラシ、講座の配布資料、参加者カード、表示物、各コーナーの説明札 | C13: 0 | D13: 1 | E13: =C13*D13 | F13: 社協内の印刷でまかなうため0円（9/15のご指示）
A14: 消耗品 | B14: 名札、紙コップ、紙皿、おしぼり、ゴミ袋、文具 | C14: 2500 | D14: 1 | E14: =C14*D14
A15: 講師・協力者へのお礼 | B15: 高橋文之さん、防災士、配食ボランティアのみなさんへ | C15: 3000 | D15: 1 | E15: =C15*D15 | F15: 品物にするか謝金にするか、規程を確認してください
B16: 合計 | E16: =SUM(E8:E15)
B17: 予算の残り | E17: =$B$4-E16 | F17: マイナスになったら、どこかを削ってください
A19: ※ 単価・数量はすべて、この表をつくった時点での仮置きです。実際の見積に置き換えてください。総額50,000円は9/2時点で示された額です。参加費は取らないことになったため（9/4）、収入はありません。チラシで定員が50人になったため、茶菓と記念品を55人分で組み直し、単価を下げました。段ボールベッドは町の備蓄から借りる想定で数量0にしています。不足分を買う場合は1台あたり約3,000円かかり、その分は記念品の単価か、盆栽の材料の数を減らして捻出することになります。防災バッグは役場総務課防災対策室からの借用のため、費用は見込んでいません。盆栽の材料は希望者15人分で組んでいます。盆栽の道具（はさみ・じょうろ・シート等）は手持ちや借用でまかなうため、予算には計上していません（9/15のご指示）。合計と残りは下の行に自動で出ます。残りがマイナスになったら、どこかを削ってください。

Sheet グラフ
A1: 準備の山と、進み具合
A2: 数字はすべて「準備リスト」から自動で数えています。状況を「完了」にすると、表もグラフも動きます。
A4: 時期 | B4: 完了 | C4: 残り | D4: 合計 | F4: 分野 | G4: 完了 | H4: 残り | I4: 合計
A5: 9/25まで | B5: =COUNTIFS(準備リスト!$D$5:$D$119,$A5,準備リスト!$I$5:$I$119,"完了") | C5: =COUNTIF(準備リスト!$D$5:$D$119,$A5)-B5 | D5: =B5+C5 | F5: A 会場をおさえる | G5: =COUNTIFS(準備リスト!$E$5:$E$119,$F5,準備リスト!$I$5:$I$119,"完了") | H5: =COUNTIF(準備リスト!$E$5:$E$119,$F5)-G5 | I5: =G5+H5
A6: 8週前 | B6: =COUNTIFS(準備リスト!$D$5:$D$119,$A6,準備リスト!$I$5:$I$119,"完了") | C6: =COUNTIF(準備リスト!$D$5:$D$119,$A6)-B6 | D6: =B6+C6 | F6: B 事務の手続き | G6: =COUNTIFS(準備リスト!$E$5:$E$119,$F6,準備リスト!$I$5:$I$119,"完了") | H6: =COUNTIF(準備リスト!$E$5:$E$119,$F6)-G6 | I6: =G6+H6
A7: 10/26まで | B7: =COUNTIFS(準備リスト!$D$5:$D$119,$A7,準備リスト!$I$5:$I$119,"完了") | C7: =COUNTIF(準備リスト!$D$5:$D$119,$A7)-B7 | D7: =B7+C7 | F7: C チラシと広報 | G7: =COUNTIFS(準備リスト!$E$5:$E$119,$F7,準備リスト!$I$5:$I$119,"完了") | H7: =COUNTIF(準備リスト!$E$5:$E$119,$F7)-G7 | I7: =G7+H7
A8: 7週前 | B8: =COUNTIFS(準備リスト!$D$5:$D$119,$A8,準備リスト!$I$5:$I$119,"完了") | C8: =COUNTIF(準備リスト!$D$5:$D$119,$A8)-B8 | D8: =B8+C8 | F8: D 参加記念品 | G8: =COUNTIFS(準備リスト!$E$5:$E$119,$F8,準備リスト!$I$5:$I$119,"完了") | H8: =COUNTIF(準備リスト!$E$5:$E$119,$F8)-G8 | I8: =G8+H8
A9: 6週前 | B9: =COUNTIFS(準備リスト!$D$5:$D$119,$A9,準備リスト!$I$5:$I$119,"完了") | C9: =COUNTIF(準備リスト!$D$5:$D$119,$A9)-B9 | D9: =B9+C9 | F9: E カフェで使う備品 | G9: =COUNTIFS(準備リスト!$E$5:$E$119,$F9,準備リスト!$I$5:$I$119,"完了") | H9: =COUNTIF(準備リスト!$E$5:$E$119,$F9)-G9 | I9: =G9+H9
A10: 5週前 | B10: =COUNTIFS(準備リスト!$D$5:$D$119,$A10,準備リスト!$I$5:$I$119,"完了") | C10: =COUNTIF(準備リスト!$D$5:$D$119,$A10)-B10 | D10: =B10+C10 | F10: F 会場に貼る表示物 | G10: =COUNTIFS(準備リスト!$E$5:$E$119,$F10,準備リスト!$I$5:$I$119,"完了") | H10: =COUNTIF(準備リスト!$E$5:$E$119,$F10)-G10 | I10: =G10+H10
A11: 4週前 | B11: =COUNTIFS(準備リスト!$D$5:$D$119,$A11,準備リスト!$I$5:$I$119,"完了") | C11: =COUNTIF(準備リスト!$D$5:$D$119,$A11)-B11 | D11: =B11+C11 | F11: G 盆栽ボランティアの準備 | G11: =COUNTIFS(準備リスト!$E$5:$E$119,$F11,準備リスト!$I$5:$I$119,"完了") | H11: =COUNTIF(準備リスト!$E$5:$E$119,$F11)-G11 | I11: =G11+H11
A12: 3週前 | B12: =COUNTIFS(準備リスト!$D$5:$D$119,$A12,準備リスト!$I$5:$I$119,"完了") | C12: =COUNTIF(準備リスト!$D$5:$D$119,$A12)-B12 | D12: =B12+C12 | F12: H 災ボラ体験の資料 | G12: =COUNTIFS(準備リスト!$E$5:$E$119,$F12,準備リスト!$I$5:$I$119,"完了") | H12: =COUNTIF(準備リスト!$E$5:$E$119,$F12)-G12 | I12: =G12+H12
A13: 2週前 | B13: =COUNTIFS(準備リスト!$D$5:$D$119,$A13,準備リスト!$I$5:$I$119,"完了") | C13: =COUNTIF(準備リスト!$D$5:$D$119,$A13)-B13 | D13: =B13+C13 | F13: I 当日の運営 | G13: =COUNTIFS(準備リスト!$E$5:$E$119,$F13,準備リスト!$I$5:$I$119,"完了") | H13: =COUNTIF(準備リスト!$E$5:$E$119,$F13)-G13 | I13: =G13+H13
A14: 1週前 | B14: =COUNTIFS(準備リスト!$D$5:$D$119,$A14,準備リスト!$I$5:$I$119,"完了") | C14: =COUNTIF(準備リスト!$D$5:$D$119,$A14)-B14 | D14: =B14+C14 | F14: J 終わったあと | G14: =COUNTIFS(準備リスト!$E$5:$E$119,$F14,準備リスト!$I$5:$I$119,"完了") | H14: =COUNTIF(準備リスト!$E$5:$E$119,$F14)-G14 | I14: =G14+H14
A15: 前日 | B15: =COUNTIFS(準備リスト!$D$5:$D$119,$A15,準備リスト!$I$5:$I$119,"完了") | C15: =COUNTIF(準備リスト!$D$5:$D$119,$A15)-B15 | D15: =B15+C15 | F15: K 体験・展示コーナーの準備 | G15: =COUNTIFS(準備リスト!$E$5:$E$119,$F15,準備リスト!$I$5:$I$119,"完了") | H15: =COUNTIF(準備リスト!$E$5:$E$119,$F15)-G15 | I15: =G15+H15
A16: 当日 | B16: =COUNTIFS(準備リスト!$D$5:$D$119,$A16,準備リスト!$I$5:$I$119,"完了") | C16: =COUNTIF(準備リスト!$D$5:$D$119,$A16)-B16 | D16: =B16+C16
A17: 当日中 | B17: =COUNTIFS(準備リスト!$D$5:$D$119,$A17,準備リスト!$I$5:$I$119,"完了") | C17: =COUNTIF(準備リスト!$D$5:$D$119,$A17)-B17 | D17: =B17+C17 | F17: 全体 | G17: =SUM(G5:G15) | H17: =SUM(H5:H15) | I17: =SUM(I5:I15)
A18: 3日以内 | B18: =COUNTIFS(準備リスト!$D$5:$D$119,$A18,準備リスト!$I$5:$I$119,"完了") | C18: =COUNTIF(準備リスト!$D$5:$D$119,$A18)-B18 | D18: =B18+C18 | F18: 進み具合 | G18: =IF(I17=0,0,G17/I17)
A19: 1週以内 | B19: =COUNTIFS(準備リスト!$D$5:$D$119,$A19,準備リスト!$I$5:$I$119,"完了") | C19: =COUNTIF(準備リスト!$D$5:$D$119,$A19)-B19 | D19: =B19+C19
A20: 2週以内 | B20: =COUNTIFS(準備リスト!$D$5:$D$119,$A20,準備リスト!$I$5:$I$119,"完了") | C20: =COUNTIF(準備リスト!$D$5:$D$119,$A20)-B20 | D20: =B20+C20
A62: 濃い緑＝完了、うすい緑＝残りです。いまは全部「未着手」なので、うすい緑だけのグラフになります。「準備リスト」の状況を「完了」にしていくと、下から緑が伸びていきます。棒が高い時期ほど、その週にやることが多いという意味です。人手を厚くする週を決めるときに使ってください。
